datasette_publish_fly/__init__.py
datasette_publish_fly-1.3.1.dist-info/LICENSE
datasette_publish_fly-1.3.1.dist-info/METADATA
datasette_publish_fly-1.3.1.dist-info/WHEEL
datasette_publish_fly-1.3.1.dist-info/entry_points.txt
datasette_publish_fly-1.3.1.dist-info/top_level.txt
datasette_publish_fly-1.3.1.dist-info/RECORD
