Metadata-Version: 2.1
Name: datasette-publish-fly
Version: 1.3.1
Summary: Datasette plugin for publishing data using Fly
Home-page: https://github.com/simonw/datasette-publish-fly
Author: Simon Willison
License: Apache License, Version 2.0
Project-URL: Issues, https://github.com/simonw/datasette-publish-fly/issues
Project-URL: CI, https://github.com/simonw/datasette-publish-fly/actions
Project-URL: Changelog, https://github.com/simonw/datasette-publish-fly/releases
License-File: LICENSE
Requires-Dist: datasette >=0.60.2
Provides-Extra: test
Requires-Dist: pytest ; extra == 'test'
Requires-Dist: pytest-mock ; extra == 'test'
Requires-Dist: cogapp ; extra == 'test'
